packnet/ARP.py
packnet/DHCP.py
packnet/DNS.py
packnet/ETHERNET.py
packnet/ICMP.py
packnet/ICMPv6.py
packnet/IPv4.py
packnet/IPv6.py
packnet/TCP.py
packnet/UDP.py
packnet/__init__.py
packnet/frame.py
packnet/general.py
packnet/interface.py
packnet/packager.py
packnet/tree.py
packnet/vendor.py
packnet/datatype/__init__.py
packnet/datatype/dtADDR.py
packnet/datatype/dtCHECKSUM.py
packnet/datatype/dtINT.py
packnet/datatype/dtIP.py
packnet/datatype/dtLEN.py
packnet/datatype/dtMAC.py
packnet/datatype/dtNAME.py
packnet-3.0.2.dist-info/LICENSE
packnet-3.0.2.dist-info/METADATA
packnet-3.0.2.dist-info/WHEEL
packnet-3.0.2.dist-info/top_level.txt
packnet-3.0.2.dist-info/RECORD
