Metadata-Version: 2.1
Name: packnet
Version: 3.0.2
Summary: Python3 package for low-level networking
Home-page: https://github.com/c0mplh4cks/packnet
Author: c0mplh4cks
License: MIT
Platform: UNKNOWN
Requires-Python: >=3
